openfermioncirq/__init__.py
openfermioncirq/_compat.py
openfermioncirq/_compat_test.py
openfermioncirq/_version.py
openfermioncirq/contrib/__init__.py
openfermioncirq/contrib/contrib_test.py
openfermioncirq/gates/__init__.py
openfermioncirq/gates/common_gates.py
openfermioncirq/gates/common_gates_test.py
openfermioncirq/gates/fermionic_simulation.py
openfermioncirq/gates/fermionic_simulation_test.py
openfermioncirq/gates/four_qubit_gates.py
openfermioncirq/gates/four_qubit_gates_test.py
openfermioncirq/gates/three_qubit_gates.py
openfermioncirq/gates/three_qubit_gates_test.py
openfermioncirq/optimization/__init__.py
openfermioncirq/optimization/algorithm.py
openfermioncirq/optimization/algorithm_test.py
openfermioncirq/optimization/black_box.py
openfermioncirq/optimization/black_box_test.py
openfermioncirq/optimization/result.py
openfermioncirq/optimization/result_test.py
openfermioncirq/optimization/scipy.py
openfermioncirq/optimization/scipy_test.py
openfermioncirq/primitives/__init__.py
openfermioncirq/primitives/bogoliubov_transform.py
openfermioncirq/primitives/bogoliubov_transform_test.py
openfermioncirq/primitives/ffft.py
openfermioncirq/primitives/ffft_test.py
openfermioncirq/primitives/optimal_givens_decomposition.py
openfermioncirq/primitives/optimal_givens_decomposition_test.py
openfermioncirq/primitives/state_preparation.py
openfermioncirq/primitives/state_preparation_test.py
openfermioncirq/primitives/swap_network.py
openfermioncirq/primitives/swap_network_test.py
openfermioncirq/testing/__init__.py
openfermioncirq/testing/example_classes.py
openfermioncirq/testing/random.py
openfermioncirq/testing/random_test.py
openfermioncirq/testing/wrapped.py
openfermioncirq/trotter/__init__.py
openfermioncirq/trotter/simulate_trotter.py
openfermioncirq/trotter/simulate_trotter_test.py
openfermioncirq/trotter/trotter_algorithm.py
openfermioncirq/trotter/trotter_algorithm_test.py
openfermioncirq/trotter/algorithms/__init__.py
openfermioncirq-0.4.0.dist-info/LICENSE
openfermioncirq-0.4.0.dist-info/METADATA
openfermioncirq-0.4.0.dist-info/WHEEL
openfermioncirq-0.4.0.dist-info/top_level.txt
openfermioncirq-0.4.0.dist-info/RECORD
