Metadata-Version: 2.1
Name: openfermioncirq
Version: 0.4.0
Summary: Quantum circuits for simulations of quantum chemistry and materials.
Home-page: https://github.com/quantumlib/OpenFermion-Cirq
Author: The OpenFermion Developers
Author-email: openfermioncirq@googlegroups.com
License: Apache 2
Platform: UNKNOWN
Requires-Python: >=3.6.5
Requires-Dist: cirq (>=0.7.0)
Requires-Dist: deprecation
Requires-Dist: numpy
Requires-Dist: openfermion (>=0.11.0)
Requires-Dist: pandas
Requires-Dist: scipy
Requires-Dist: sympy
